utils/config_generator.py
utils/file_utils.py
utils/swagger_helper.py
utils/typescript_generator.py
zmdms_mcp_swagger-0.1.3.dist-info/METADATA
zmdms_mcp_swagger-0.1.3.dist-info/WHEEL
zmdms_mcp_swagger-0.1.3.dist-info/top_level.txt
zmdms_mcp_swagger-0.1.3.dist-info/RECORD
