Metadata-Version: 2.4
Name: zmdms-mcp-swagger
Version: 0.1.3
Summary: Add your description here
Requires-Python: >=3.13
Requires-Dist: mcp[cli]>=1.10.1
